multixrank/Bipartite.py
multixrank/BipartiteAll.py
multixrank/ConfigParser.py
multixrank/Multiplex.py
multixrank/MultiplexAll.py
multixrank/MultiplexLayer.py
multixrank/Output.py
multixrank/ParameterEta.py
multixrank/ParameterLambda.py
multixrank/Parameters.py
multixrank/PathManager.py
multixrank/Seed.py
multixrank/TransitionMatrix.py
multixrank/__init__.py
multixrank/constants.py
multixrank/logger_setup.py
multixrank/data_example/airport/config_full.yml
multixrank/data_example/airport/config_minimal.yml
multixrank/data_example/airport/seeds.txt
multixrank/data_example/airport/bipartite/1_2.tsv
multixrank/data_example/airport/bipartite/1_3.tsv
multixrank/data_example/airport/bipartite/2_3.tsv
multixrank/data_example/airport/multiplex/1/FR26.tsv
multixrank/data_example/airport/multiplex/1/FR3.tsv
multixrank/data_example/airport/multiplex/1/FR7.tsv
multixrank/data_example/airport/multiplex/2/UK15.tsv
multixrank/data_example/airport/multiplex/2/UK26.tsv
multixrank/data_example/airport/multiplex/2/UK3.tsv
multixrank/data_example/airport/multiplex/3/G1.tsv
multixrank/data_example/airport/multiplex/3/G24.tsv
multixrank/data_example/airport/multiplex/3/G6.tsv
multixrank/tests/__init__.py
multixrank/tests/test_airport.py
multixrank/tests/test_biological.py
multixrank/tests/test_hetionet.py
multixrank-0.3.dist-info/LICENSE.txt
multixrank-0.3.dist-info/METADATA
multixrank-0.3.dist-info/WHEEL
multixrank-0.3.dist-info/top_level.txt
multixrank-0.3.dist-info/RECORD
