Metadata-Version: 2.1
Name: multixrank
Version: 0.3
Summary: MultiXrank - Universal Multilayer Exploration by Random Walk with Restart. MultiXrank is a Python package for the exploration of heterogeneous multilayer networks, with random walk with restart method. It permits prioritization of nodes between full heterogeneous networks, whatever their complexities.
Home-page: https://multixrank.readthedocs.io
Author: Anthony Baptista, Aitor González, Anaïs Baudot
Author-email: anthony.baptista@qmul.ac.uk, aitor.gonzalez@univ-amu.fr
License: MIT
Classifier: Development Status :: 4 - Beta
Classifier: Environment :: Console
Classifier: Intended Audience :: Developers
Classifier: Intended Audience :: Science/Research
Classifier: License :: OSI Approved :: MIT License
Classifier: Operating System :: OS Independent
Classifier: Programming Language :: Python :: 3
Classifier: Programming Language :: Python :: 3.7
Classifier: Programming Language :: Python :: 3.8
Classifier: Programming Language :: Python :: 3.9
Classifier: Programming Language :: Python :: 3.10
Classifier: Programming Language :: Python :: 3.11
Classifier: Programming Language :: Python :: 3 :: Only
Classifier: Topic :: Software Development :: Libraries :: Python Modules
Classifier: Topic :: Scientific/Engineering :: Bio-Informatics
Classifier: Topic :: Scientific/Engineering :: Information Analysis
Classifier: Topic :: Scientific/Engineering :: Mathematics
Classifier: Topic :: Scientific/Engineering :: Physics
License-File: LICENSE.txt
Requires-Dist: networkx
Requires-Dist: numpy
Requires-Dist: pandas
Requires-Dist: psutil
Requires-Dist: pyyaml
Requires-Dist: scipy
